benchmark/__init__.py
benchmark/main.py
benchmark/utils/__init__.py
benchmark/utils/cost_calculator.py
benchmark/utils/data_loader.py
benchmark/utils/evaluator.py
benchmark/utils/output_manager.py
benchmark/utils/progress_tracker.py
vibex/__init__.py
vibex/run.py
vibex/builtin_tools/__init__.py
vibex/builtin_tools/context.py
vibex/builtin_tools/document.py
vibex/builtin_tools/file.py
vibex/builtin_tools/file_clean.py
vibex/builtin_tools/memory.py
vibex/builtin_tools/research.py
vibex/builtin_tools/search.py
vibex/builtin_tools/web.py
vibex/builtin_tools/web_crawl4ai.py
vibex/cli/__init__.py
vibex/cli/bootstrap.py
vibex/cli/debug.py
vibex/cli/main.py
vibex/cli/parser.py
vibex/cli/status.py
vibex/cli/templates.py
vibex/cli/tools.py
vibex/cli/commands/web.py
vibex/cli/commands/web_simple.py
vibex/config/__init__.py
vibex/config/agent_loader.py
vibex/config/prompt_loader.py
vibex/config/team_loader.py
vibex/core/__init__.py
vibex/core/agent.py
vibex/core/brain.py
vibex/core/config.py
vibex/core/event.py
vibex/core/exceptions.py
vibex/core/guardrails.py
vibex/core/handoff_evaluator.py
vibex/core/memory.py
vibex/core/message.py
vibex/core/message_builder.py
vibex/core/plan.py
vibex/core/project.py
vibex/core/task.py
vibex/core/task_executor.py
vibex/core/tool.py
vibex/core/xagent.py
vibex/event/__init__.py
vibex/event/api.py
vibex/event/bus.py
vibex/event/middleware.py
vibex/event/models.py
vibex/event/subscribers.py
vibex/event/types.py
vibex/memory/__init__.py
vibex/memory/backend.py
vibex/memory/factory.py
vibex/memory/mem0_backend.py
vibex/memory/memory_system.py
vibex/memory/models.py
vibex/memory/synthesis_engine.py
vibex/memory/types.py
vibex/observability/__init__.py
vibex/observability/monitor.py
vibex/observability/web_app.py
vibex/observability/static/logo.png
vibex/observability/templates/artifacts.jinja2
vibex/observability/templates/base.jinja2
vibex/observability/templates/configuration.jinja2
vibex/observability/templates/dashboard.jinja2
vibex-0.30.1.dist-info/licenses/LICENSE
vibex-0.30.1.dist-info/METADATA
vibex-0.30.1.dist-info/WHEEL
vibex-0.30.1.dist-info/entry_points.txt
vibex-0.30.1.dist-info/top_level.txt
vibex-0.30.1.dist-info/RECORD
