Metadata-Version: 2.4
Name: vibex
Version: 0.30.1
Summary: VibeX - An Opinionated Multi-Agent Framework
Author-email: Dustland Team <hi@dustland.ai>
License-Expression: Apache-2.0
Project-URL: Homepage, https://github.com/dustland/vibex
Project-URL: Bug Tracker, https://github.com/dustland/vibex/issues
Classifier: Programming Language :: Python :: 3.11
Classifier: Operating System :: OS Independent
Requires-Python: >=3.11
License-File: LICENSE
Requires-Dist: fastapi>=0.104.0
Requires-Dist: uvicorn>=0.24.0
Requires-Dist: pydantic>=2.7.1
Requires-Dist: python-dotenv>=1.0.0
Requires-Dist: pyyaml>=6.0.1
Requires-Dist: rich>=13.6.0
Requires-Dist: loguru
Requires-Dist: litellm
Requires-Dist: openai>=1.0.0
Requires-Dist: google-search-results>=2.4.2
Requires-Dist: mem0ai>=0.1.106
Requires-Dist: mcp>=1.4.1
Requires-Dist: firecrawl-py>=0.0.16
Requires-Dist: browser-use>=0.1.0
Requires-Dist: numpy>=1.24.3
Requires-Dist: requests>=2.31.0
Requires-Dist: httpx>=0.24.0
Requires-Dist: aiohttp>=3.8.0
Requires-Dist: beautifulsoup4>=4.12.0
Requires-Dist: markdown>=3.4.0
Requires-Dist: jinja2>=3.1.6
Requires-Dist: sqlmodel>=0.0.8
Requires-Dist: sqlalchemy>=2.0.0
Requires-Dist: chromadb>=1.0.12
Requires-Dist: pyarrow>=19.0.1
Requires-Dist: aiofiles>=24.1.0
Requires-Dist: gitpython>=3.1.44
Requires-Dist: pygithub>=2.6.1
Requires-Dist: crawl4ai>=0.7.0
Requires-Dist: playwright>=1.52.0
Requires-Dist: sse-starlette>=1.6.5
Provides-Extra: dev
Requires-Dist: pytest; extra == "dev"
Requires-Dist: pytest-cov; extra == "dev"
Requires-Dist: pytest-asyncio; extra == "dev"
Requires-Dist: uv; extra == "dev"
Provides-Extra: code-execution
Requires-Dist: daytona>=0.1.0; extra == "code-execution"
Provides-Extra: web-automation
Requires-Dist: browser-use>=0.1.0; extra == "web-automation"
Requires-Dist: playwright>=1.40.0; extra == "web-automation"
Provides-Extra: all
Requires-Dist: streamlit>=1.32.0; extra == "all"
Requires-Dist: daytona>=0.1.0; extra == "all"
Requires-Dist: browser-use>=0.1.0; extra == "all"
Requires-Dist: playwright>=1.40.0; extra == "all"
Dynamic: license-file
